pyshopee/__init__.py
pyshopee/base.py
pyshopee/client.py
pyshopee/discount.py
pyshopee/image.py
pyshopee/item.py
pyshopee/logistic.py
pyshopee/order.py
pyshopee/public.py
pyshopee/returns.py
pyshopee/rma.py
pyshopee/shop.py
pyshopee/shopcategory.py
pyshopee/toppicks.py
pyshopee-1.3.9.dist-info/LICENSE
pyshopee-1.3.9.dist-info/METADATA
pyshopee-1.3.9.dist-info/WHEEL
pyshopee-1.3.9.dist-info/top_level.txt
pyshopee-1.3.9.dist-info/zip-safe
pyshopee-1.3.9.dist-info/RECORD
